asserto/__init__.py
asserto/_api.py
asserto/_asserto.py
asserto/_constants.py
asserto/_decorators.py
asserto/_error_handling.py
asserto/_exc_handling.py
asserto/_exceptions.py
asserto/_protocols.py
asserto/_softly.py
asserto/_templates.py
asserto/_types.py
asserto/_util.py
asserto/_warnings.py
asserto/descriptors/__init__.py
asserto/descriptors/_abc.py
asserto/descriptors/_validators.py
asserto/handlers/__init__.py
asserto/handlers/_base.py
asserto/handlers/_date.py
asserto/handlers/_files.py
asserto/handlers/_handler.py
asserto/handlers/_numeric.py
asserto/handlers/_regex.py
asserto/mixins/__init__.py
asserto/mixins/_base.py
asserto/mixins/_string_mixin.py
asserto/mixins/_utils.py
asserto/py.typed
asserto-0.1.4.dist-info/LICENSE
asserto-0.1.4.dist-info/METADATA
asserto-0.1.4.dist-info/WHEEL
asserto-0.1.4.dist-info/RECORD
